README.rst
setup.py
src/pypi_data/__init__.py
src/pypi_data/__main__.py
src/pypi_data.egg-info/PKG-INFO
src/pypi_data.egg-info/SOURCES.txt
src/pypi_data.egg-info/dependency_links.txt
src/pypi_data.egg-info/entry_points.txt
src/pypi_data.egg-info/top_level.txt